pyscratch/__init__.py
pyscratch/backdrops.py
pyscratch/base.py
pyscratch/sprites.py
pyscratch-0.2.6.dist-info/METADATA
pyscratch-0.2.6.dist-info/WHEEL
pyscratch-0.2.6.dist-info/top_level.txt
pyscratch-0.2.6.dist-info/RECORD
