Metadata-Version: 2.1
Name: pyscratch
Version: 0.2.6
Summary: Education tool, provide scratch enviroment and API in python, help children learn python easily
Home-page: http://www.openscratch.com/
Author: shaolizhi
Author-email: 53733522@qq.com
License: MIT
Keywords: pyscratch scratch children education learn python game easy
Platform: UNKNOWN
Requires-Dist: pygame
